{
  "subjectId": "science",
  "eraId": "sci1-earth",
  "topicId": "sci1-earthquake",
  "name": "動き続ける大地",
  "subtitle": "地震のゆれ・P波とS波・プレート・地震への備え",
  "icon": "🌍",
  "order": 2,
  "videos": [],
  "flashcards": [
    {
      "id": "fc1",
      "front": "{震源|しんげん}",
      "back": "地下で、岩盤のずれが最初に起きた場所を何という？",
      "explanation": "地震が発生した場所であり、地下の点として考える。",
      "difficulty": "basic"
    },
    {
      "id": "fc2",
      "front": "{震央|しんおう}",
      "back": "震源の真上にあたる地表の地点を何という？",
      "explanation": "観測点から震央までの距離を震央距離、震源までの距離を震源距離という。",
      "difficulty": "basic"
    },
    {
      "id": "fc3",
      "front": "{震度|しんど}",
      "back": "ある地点での地震によるゆれの大きさを表すものを何という？",
      "explanation": "日本では0〜7（5・6は強・弱の2階級）の10階級に分けられる。観測地点ごとに変わる。",
      "difficulty": "basic"
    },
    {
      "id": "fc4",
      "front": "マグニチュード",
      "back": "地震の規模を表すものを何という？",
      "explanation": "記号Mで表す。1つの地震に対して基本的に1つの値で、値が1大きくなるとエネルギーは約30倍、2大きくなると約1000倍になる。",
      "difficulty": "basic"
    },
    {
      "id": "fc5",
      "front": "P波",
      "back": "震源で発生し、S波より速く伝わる地震波を何という？",
      "explanation": "P波が到達すると初期微動（小さなゆれ）が始まる。",
      "difficulty": "standard"
    },
    {
      "id": "fc6",
      "front": "S波",
      "back": "P波より遅く伝わり、あとから到達する地震波を何という？",
      "explanation": "S波が到達すると主要動（大きなゆれ）が始まる。",
      "difficulty": "standard"
    },
    {
      "id": "fc7",
      "front": "{初期微動|しょきびどう}",
      "back": "地震で初めに起こる小さなゆれを何という？",
      "explanation": "P波が到達することで起こる。",
      "difficulty": "standard"
    },
    {
      "id": "fc8",
      "front": "{主要動|しゅようどう}",
      "back": "初期微動のあとから起こる大きなゆれを何という？",
      "explanation": "S波が到達することで起こり、被害に関係しやすい。",
      "difficulty": "standard"
    },
    {
      "id": "fc9",
      "front": "{初期微動継続時間|しょきびどうけいぞくじかん}",
      "back": "初期微動が始まってから主要動が始まるまでの時間を何という？",
      "explanation": "P波とS波の到着時刻の差にあたり、震源から遠いほど長くなる。",
      "difficulty": "standard"
    },
    {
      "id": "fc10",
      "front": "震源から遠いほど長くなる",
      "back": "震源からの距離が大きくなると、初期微動継続時間はどうなる？",
      "explanation": "波の速さが一定なら、初期微動継続時間は震源からの距離に比例する。",
      "difficulty": "standard"
    },
    {
      "id": "fc11",
      "front": "速さ＝距離÷時間",
      "back": "地震の波が伝わる速さを求める式は？",
      "explanation": "単位は秒速km（km/s）を使うことが多い。距離＝速さ×時間、時間＝距離÷速さと変形できる。",
      "difficulty": "standard"
    },
    {
      "id": "fc12",
      "front": "{秒速|びょうそく}7km",
      "back": "震源から70km離れた地点にP波が10秒で届いた。P波の速さは秒速何km？",
      "explanation": "速さ＝距離÷時間＝70÷10＝秒速7km。",
      "difficulty": "standard"
    },
    {
      "id": "fc13",
      "front": "10秒",
      "back": "P波が10時05分10秒、S波が10時05分20秒に届いた。初期微動継続時間は何秒？",
      "explanation": "20秒−10秒＝10秒。S波到着時刻−P波到着時刻で求める。",
      "difficulty": "standard"
    },
    {
      "id": "fc14",
      "front": "プレート",
      "back": "地球の表面をおおう、厚さ100kmほどの岩盤を何という？",
      "explanation": "1年間に数cm〜十数cmの速さで決まった向きに動いている。",
      "difficulty": "basic"
    },
    {
      "id": "fc15",
      "front": "{海溝|かいこう}",
      "back": "海洋プレートが大陸プレートの下にしずみこむところにできる、深い溝のような地形を何という？",
      "explanation": "日本列島と海溝の間では震源が多く分布する。",
      "difficulty": "standard"
    },
    {
      "id": "fc16",
      "front": "{断層|だんそう}",
      "back": "岩石の一部が破壊されてできる、岩盤のずれを何という？",
      "explanation": "断層ができるとき発生するゆれが地表に伝わると地震になる。",
      "difficulty": "standard"
    },
    {
      "id": "fc17",
      "front": "{活断層|かつだんそう}",
      "back": "過去にくり返しずれたことがあり、今後もずれる可能性がある断層を何という？",
      "explanation": "陸の浅いところで活断層がずれると、震源が浅く震度が大きくなることがある。",
      "difficulty": "advanced"
    },
    {
      "id": "fc18",
      "front": "{津波|つなみ}",
      "back": "海溝付近の地震で海底がもち上がり、海水が大きなかたまりとなって陸地におし寄せる現象を何という？",
      "explanation": "海底が急にもち上がることで発生する。",
      "difficulty": "standard"
    },
    {
      "id": "fc19",
      "front": "{隆起|りゅうき}",
      "back": "地震などによって大地がもち上がる現象を何という？",
      "explanation": "反対に大地がしずむ現象を沈降という。",
      "difficulty": "standard"
    },
    {
      "id": "fc20",
      "front": "{沈降|ちんこう}",
      "back": "地震などによって大地がしずむ現象を何という？",
      "explanation": "隆起と反対の動き。長い年月の大地の変動で起こる。",
      "difficulty": "standard"
    },
    {
      "id": "fc21",
      "front": "{液状化現象|えきじょうかげんしょう}",
      "back": "砂の多い土地に大きなゆれが加わり、土地が液体のようにふるまう現象を何という？",
      "explanation": "建物が傾いたり、マンホールがうき上がったり、泥水がふき出したりする。",
      "difficulty": "standard"
    },
    {
      "id": "fc22",
      "front": "{緊急地震速報|きんきゅうじしんそくほう}",
      "back": "震源に近い観測所でとらえたP波の情報をもとに、大きなゆれの前に知らせる予報・警報を何という？",
      "explanation": "P波がS波より速いことを利用している。震源に近い場所では間に合わないことがある。",
      "difficulty": "standard"
    },
    {
      "id": "fc23",
      "front": "P波がS波より先に届くこと",
      "back": "緊急地震速報のしくみに利用されている、地震波の性質は？",
      "explanation": "先に届くP波を検知し、大きなゆれ（S波）が来る前に警告を出す。",
      "difficulty": "advanced"
    },
    {
      "id": "fc24",
      "front": "震度は地点ごとのゆれだから",
      "back": "「震度が大きい地震は必ずマグニチュードも大きい」とは限らない理由は？",
      "explanation": "震度は震源からの距離や地盤で変わり、マグニチュードとは別のものだから。",
      "difficulty": "advanced"
    },
    {
      "id": "fc25",
      "front": "同心円になる",
      "back": "ゆれ始めの時刻が同じ地点をなめらかな曲線で結ぶと、震央を中心としてどのような形になる？",
      "explanation": "「同心円」は中心が同じ円がいくつも重なった形のこと。地震のゆれは震央から四方八方へ同じように伝わるため、ゆれ始めの時刻が同じ地点を結ぶと震央を中心とした同心円状になる。",
      "difficulty": "advanced"
    },
    {
      "id": "fc27",
      "front": "10階級",
      "back": "日本で使われている震度は、いくつの階級に分けられている？",
      "explanation": "0〜7のうち、5と6がそれぞれ強・弱の2階級に分かれるため全部で10階級になる。",
      "difficulty": "standard"
    },
    {
      "id": "fc28",
      "front": "{震央|しんおう}付近",
      "back": "ふつう、地震のゆれ（震度）が最も大きくなるのは震央からどのあたりか？",
      "explanation": "震源に近い震央付近ほどゆれが大きく、遠ざかるほど小さくなる。",
      "difficulty": "standard"
    },
    {
      "id": "fc29",
      "front": "おもり",
      "back": "地震計で、地面がゆれても、慣性によってほとんど動かずに残る部分は？",
      "explanation": "地震計は、おもりが慣性でほとんど動かないのに対し、台や記録紙が地面とともに動く。そのずれがゆれとして記録紙に記録される。",
      "difficulty": "advanced"
    },
    {
      "id": "fc30",
      "front": "{海溝型地震|かいこうがたじしん}",
      "back": "海洋プレートが大陸プレートの下にしずみこみ、ひずみにたえきれなくなった大陸プレートがはね上がって起こる地震を何という？",
      "explanation": "震源付近の海底がもち上がるため、津波が発生することがある。",
      "difficulty": "advanced"
    },
    {
      "id": "fc31",
      "front": "はね上がる",
      "back": "海溝型地震で、しずみこむ海洋プレートに引きずられた大陸プレートはどうなって地震が起こる？",
      "explanation": "ひずみが限界に達すると、大陸プレートの先端がもとにもどろうとしてはね上がる。",
      "difficulty": "advanced"
    },
    {
      "id": "fc32",
      "front": "太平洋側で浅く、日本列島の下ほど深い",
      "back": "日本付近の海溝型地震で、震源の深さは太平洋側から日本列島の下に向かってどう変化する？",
      "explanation": "海洋プレートがななめにしずみこむため、内陸に向かうほど震源が深くなる。",
      "difficulty": "advanced"
    }
  ],
  "quiz": {
    "questions": [
      {
        "id": "q1",
        "question": "地下で、岩盤のずれが最初に起きた場所を何といいますか。",
        "options": [
          "震源",
          "震央",
          "震度",
          "海溝"
        ],
        "correctIndex": 0,
        "explanation": "地震が発生した地下の場所が震源です。震央はその真上の地表の地点です。",
        "difficulty": "basic"
      },
      {
        "id": "q2",
        "question": "震源の真上にあたる地表の地点を何といいますか。",
        "options": [
          "震源",
          "震度",
          "震央",
          "断層"
        ],
        "correctIndex": 2,
        "explanation": "震央は震源の真上の地表の地点です。",
        "difficulty": "basic"
      },
      {
        "id": "q3",
        "question": "ある地点でのゆれの大きさを表し、観測地点によって変わるものはどれですか。",
        "options": [
          "マグニチュード",
          "震度",
          "初期微動",
          "震源"
        ],
        "correctIndex": 1,
        "explanation": "震度は地点ごとのゆれの大きさで、日本では0〜7の10階級に分けられます。",
        "difficulty": "basic"
      },
      {
        "id": "q4",
        "question": "地震の規模を表すものはどれですか。",
        "options": [
          "震度",
          "初期微動",
          "マグニチュード",
          "主要動"
        ],
        "correctIndex": 2,
        "explanation": "マグニチュードは記号Mで表し、地震そのものの規模（放出されるエネルギー）を表す。震度は各地点でのゆれの強さを表す別のもの。",
        "difficulty": "basic"
      },
      {
        "id": "q5",
        "question": "P波について正しい説明はどれですか。",
        "options": [
          "S波より遅く伝わる",
          "大きなゆれを起こす",
          "S波より先に到達する",
          "地表をゆらさない"
        ],
        "correctIndex": 2,
        "explanation": "P波はS波より速く伝わるため先に到達し、小さなゆれである初期微動を起こします。",
        "difficulty": "standard"
      },
      {
        "id": "q6",
        "question": "S波が到達することで起こる、あとから来る大きなゆれを何といいますか。",
        "options": [
          "初期微動",
          "主要動",
          "震央",
          "余震"
        ],
        "correctIndex": 1,
        "explanation": "S波が到達すると大きなゆれである主要動が始まります。",
        "difficulty": "standard"
      },
      {
        "id": "q7",
        "question": "初期微動継続時間とはどの時間ですか。",
        "options": [
          "地震発生からP波到着まで",
          "P波到着からS波到着まで",
          "S波到着から地震終了まで",
          "震度が決まるまで"
        ],
        "correctIndex": 1,
        "explanation": "初期微動継続時間は、P波が到達してからS波が到達するまでの時間です。",
        "difficulty": "standard"
      },
      {
        "id": "q8",
        "question": "震源から遠い地点ほど、初期微動継続時間はどうなりますか。",
        "options": [
          "短くなる",
          "変わらない",
          "震源の深さで決まる",
          "長くなる"
        ],
        "correctIndex": 3,
        "explanation": "初期微動継続時間は震源からの距離に比例する。遠いほどP波とS波の到着時刻の差が大きくなり、継続時間は長くなる。",
        "difficulty": "standard"
      },
      {
        "id": "q9",
        "question": "震源から90km離れた地点にP波が15秒で届きました。P波の速さは秒速何kmですか。",
        "options": [
          "秒速5km",
          "秒速6km",
          "秒速8km",
          "秒速9km"
        ],
        "correctIndex": 1,
        "explanation": "速さ＝距離÷時間＝90÷15＝秒速6kmです。",
        "difficulty": "standard"
      },
      {
        "id": "q10",
        "question": "S波の速さが秒速4kmのとき、震源から100km離れた地点にS波が届くのは何秒後ですか。",
        "options": [
          "20秒後",
          "25秒後",
          "30秒後",
          "40秒後"
        ],
        "correctIndex": 1,
        "explanation": "時間＝距離÷速さ＝100÷4＝25秒です。",
        "difficulty": "standard"
      },
      {
        "id": "q11",
        "question": "P波が10時08分12秒、S波が10時08分27秒に到着しました。初期微動継続時間は何秒ですか。",
        "options": [
          "12秒",
          "15秒",
          "27秒",
          "39秒"
        ],
        "correctIndex": 1,
        "explanation": "S波到着−P波到着＝27秒−12秒＝15秒です。",
        "difficulty": "standard"
      },
      {
        "id": "q12",
        "question": "P波の速さが秒速7km、S波の速さが秒速4kmのとき、震源から56kmの地点で、P波とS波の到着時刻の差は何秒ですか。",
        "options": [
          "6秒",
          "8秒",
          "14秒",
          "22秒"
        ],
        "correctIndex": 0,
        "explanation": "P波の到着は56÷7＝8秒、S波は56÷4＝14秒。差は14−8＝6秒です。",
        "difficulty": "advanced"
      },
      {
        "id": "q13",
        "question": "同じ地震で、A地点の初期微動継続時間は6秒、B地点は18秒でした。震源に近いのはどちらですか。",
        "options": [
          "B地点",
          "どちらも同じ",
          "判断できない",
          "A地点"
        ],
        "correctIndex": 3,
        "explanation": "初期微動継続時間が短い地点ほど震源に近いので、6秒のA地点が震源に近いです。",
        "difficulty": "standard"
      },
      {
        "id": "q14",
        "question": "ある地震で、震源からの距離が2倍の地点では、地震波が届くまでの時間はどうなりますか。ただし速さは一定とします。",
        "options": [
          "変わらない",
          "半分になる",
          "2倍になる",
          "4倍になる"
        ],
        "correctIndex": 2,
        "explanation": "時間＝距離÷速さなので、距離が2倍になれば時間も2倍になります。",
        "difficulty": "advanced"
      },
      {
        "id": "q15",
        "question": "P波の速さが秒速8km、S波の速さが秒速4kmで伝わります。初期微動継続時間が10秒の地点は、震源から何km離れていますか。",
        "options": [
          "40km",
          "60km",
          "80km",
          "120km"
        ],
        "correctIndex": 2,
        "explanation": "震源距離をdとすると、d÷4−d÷8＝d÷8＝10秒。よってd＝80kmです。",
        "difficulty": "advanced"
      },
      {
        "id": "q16",
        "question": "地球の表面をおおう、厚さ100kmほどの岩盤を何といいますか。",
        "options": [
          "プレート",
          "断層",
          "海溝",
          "震源"
        ],
        "correctIndex": 0,
        "explanation": "プレートは地球の表面をおおう岩盤で、少しずつ動いています。",
        "difficulty": "basic"
      },
      {
        "id": "q17",
        "question": "海洋プレートが大陸プレートの下にしずみこむところにできる、深い溝のような地形を何といいますか。",
        "options": [
          "断層",
          "海溝",
          "震央",
          "柱状図"
        ],
        "correctIndex": 1,
        "explanation": "海溝は海洋プレートがしずみこむところにできる深い地形で、付近で大きな地震が起こりやすいです。",
        "difficulty": "standard"
      },
      {
        "id": "q18",
        "question": "岩石の一部が破壊されてできる、岩盤のずれを何といいますか。",
        "options": [
          "しゅう曲",
          "海溝",
          "断層",
          "隆起"
        ],
        "correctIndex": 2,
        "explanation": "岩盤がずれて断層ができるとき発生したゆれが、地表に伝わって地震になります。",
        "difficulty": "standard"
      },
      {
        "id": "q19",
        "question": "過去にくり返しずれたことがあり、今後もずれる可能性がある断層を何といいますか。",
        "options": [
          "活断層",
          "海溝",
          "鍵層",
          "震央"
        ],
        "correctIndex": 0,
        "explanation": "活断層は今後も地震を起こす可能性がある断層です。",
        "difficulty": "standard"
      },
      {
        "id": "q20",
        "question": "海溝付近の地震で海底が急にもち上がると、発生することがある現象はどれですか。",
        "options": [
          "液状化",
          "津波",
          "火砕流",
          "しゅう曲"
        ],
        "correctIndex": 1,
        "explanation": "海底がもち上がると海水が大きなかたまりとなって陸地におし寄せる津波が発生することがあります。",
        "difficulty": "standard"
      },
      {
        "id": "q21",
        "question": "砂の多い土地に大きなゆれが加わり、土地が液体のようにふるまう現象を何といいますか。",
        "options": [
          "液状化現象",
          "隆起",
          "沈降",
          "風化"
        ],
        "correctIndex": 0,
        "explanation": "液状化現象では建物が傾いたり、マンホールがうき上がったり、泥水がふき出したりします。",
        "difficulty": "standard"
      },
      {
        "id": "q22",
        "question": "地震などによって大地がもち上がる現象を何といいますか。",
        "options": [
          "沈降",
          "液状化",
          "津波",
          "隆起"
        ],
        "correctIndex": 3,
        "explanation": "大地がもち上がる現象が隆起で、しずむ現象が沈降です。",
        "difficulty": "standard"
      },
      {
        "id": "q23",
        "question": "震源に近い観測所でとらえたP波の情報をもとに、大きなゆれが来る前に知らせる予報・警報を何といいますか。",
        "options": [
          "緊急地震速報",
          "津波警報",
          "ハザードマップ",
          "震度速報"
        ],
        "correctIndex": 0,
        "explanation": "緊急地震速報は、先に届くP波を検知して大きなゆれ（S波）の前に知らせるしくみです。",
        "difficulty": "standard"
      },
      {
        "id": "q24",
        "question": "緊急地震速報に利用される考え方として最も関係が深いものはどれですか。",
        "options": [
          "S波がP波より速いこと",
          "震度が全国で同じこと",
          "P波がS波より先に届くこと",
          "火山灰が風で運ばれること"
        ],
        "correctIndex": 2,
        "explanation": "P波がS波より速く先に届くことを利用して、大きなゆれを予測します。",
        "difficulty": "standard"
      },
      {
        "id": "q25",
        "question": "日本列島付近で接しているプレートの数として正しいものはどれですか。",
        "options": [
          "2つ",
          "3つ",
          "6つ",
          "4つ"
        ],
        "correctIndex": 3,
        "explanation": "日本列島付近では大陸プレート（ユーラシア・北アメリカ）と海洋プレート（太平洋・フィリピン海）の4つが接しています。",
        "difficulty": "standard"
      },
      {
        "id": "q26",
        "question": "「震度が大きい地震は、必ずマグニチュードも大きい」とは限らない理由はどれですか。",
        "options": [
          "震度は観測地点ごとのゆれの強さを表すから",
          "マグニチュードは地点ごとに変わるから",
          "震度は地震が起きた回数で決まるから",
          "マグニチュードは各地の震度を平均した値だから"
        ],
        "correctIndex": 0,
        "explanation": "震度は観測地点ごとのゆれの強さで、震源からの距離や地盤で変わる。マグニチュードは地震そのものの規模で1つの値。だから震度が大きくてもマグニチュードが大きいとは限らない。",
        "difficulty": "advanced"
      },
      {
        "id": "q27",
        "question": "ゆれ始めの時刻が同じ地点をなめらかな曲線で結ぶと、震央を中心としてどのような形になりますか。",
        "options": [
          "まっすぐな直線",
          "同心円",
          "三角形",
          "ばらばらの点"
        ],
        "correctIndex": 1,
        "explanation": "地震のゆれは震源から四方八方に伝わるため、ゆれ始めの時刻が同じ地点を結ぶと震央を中心とした同心円になります。",
        "difficulty": "advanced"
      },
      {
        "id": "q28",
        "question": "震源で発生したP波とS波について、正しい説明はどれですか。",
        "options": [
          "P波が発生したあとにS波が発生する",
          "S波が発生したあとにP波が発生する",
          "P波とS波が同時に発生し、P波の方が速く伝わる",
          "P波とS波が同時に発生し、S波の方が速く伝わる"
        ],
        "correctIndex": 2,
        "explanation": "P波とS波は震源で同時に発生しますが、P波の方が速く伝わるため、各地点には先にP波が到達します。",
        "difficulty": "advanced"
      },
      {
        "id": "q29",
        "question": "マグニチュードが2大きい地震では、放出されるエネルギーはおよそ何倍になりますか。",
        "options": [
          "約2倍",
          "約30倍",
          "約60倍",
          "約1000倍"
        ],
        "correctIndex": 3,
        "explanation": "マグニチュードが1大きくなるとエネルギーは約30倍、2大きくなると約1000倍になります。",
        "difficulty": "advanced"
      },
      {
        "id": "q30",
        "question": "海溝型地震が起こるしくみとして、正しい順番に並べたものはどれですか。",
        "options": [
          "海洋プレートがしずみこむ→大陸プレートがひずむ→大陸プレートがはね上がる",
          "大陸プレートがはね上がる→海洋プレートがしずみこむ→大陸プレートがひずむ",
          "大陸プレートがひずむ→海洋プレートがしずみこむ→大陸プレートがはね上がる",
          "海洋プレートがしずみこむ→大陸プレートがはね上がる→大陸プレートがひずむ"
        ],
        "correctIndex": 0,
        "explanation": "海洋プレートがしずみこみ、引きずられた大陸プレートがひずみ、限界に達するとはね上がって地震が起こります。",
        "difficulty": "advanced"
      },
      {
        "id": "q31",
        "question": "P波が地中を伝わる速さとして、最も適切なものはどれですか。",
        "options": [
          "秒速6〜8km",
          "秒速60〜80km",
          "秒速0.6〜0.8km",
          "時速6〜8km"
        ],
        "correctIndex": 0,
        "explanation": "P波はおよそ秒速6〜8kmで伝わり、S波はおよそ秒速3〜5kmで、P波の方が速いです。",
        "difficulty": "standard"
      },
      {
        "id": "q32",
        "question": "P波の速さが秒速7km、S波の速さが秒速4kmのとき、震源から84kmの地点での初期微動継続時間は何秒ですか。",
        "options": [
          "6秒",
          "12秒",
          "21秒",
          "9秒"
        ],
        "correctIndex": 3,
        "explanation": "P波の到着は84÷7＝12秒、S波は84÷4＝21秒。差は21−12＝9秒です。",
        "difficulty": "advanced"
      },
      {
        "id": "q33",
        "question": "同じ地震で、震源距離60kmの地点の初期微動継続時間が9秒でした。震源距離100kmの地点での初期微動継続時間は何秒ですか。",
        "options": [
          "6秒",
          "9秒",
          "12秒",
          "15秒"
        ],
        "correctIndex": 3,
        "explanation": "初期微動継続時間は震源距離に比例するので、60km:9秒＝100km:x、x＝9×100÷60＝15秒です。",
        "difficulty": "advanced"
      },
      {
        "id": "q34",
        "question": "地震計が地面のゆれを記録できるのは、どのようなしくみによりますか。",
        "options": [
          "記録紙が地面より速く回って差を打ち消すから",
          "ばねがゆれを電気の信号に変えて記録するから",
          "おもりは動かず、記録紙が地面とともに動くから",
          "ペンが地面のゆれを感じて自分で動いてかくから"
        ],
        "correctIndex": 2,
        "explanation": "ばねでつるしたおもりは慣性でほとんど動かず、台や記録紙が地面とともに動くため、そのずれがゆれとして記録される。",
        "difficulty": "advanced"
      }
    ]
  }
}
